pure_mcp/__init__.py
pure_mcp/_version.py
pure_mcp/example.py
pure_mcp/core/__init__.py
pure_mcp/core/client.py
pure_mcp/core/context.py
pure_mcp/core/message.py
pure_mcp/core/session.py
pure_mcp/transport/__init__.py
pure_mcp/transport/http_utils.py
pure_mcp/transport/sse.py
pure_mcp/transport/streamable_http.py
pure_mcp/transport/streams.py
pure_mcp/types/__init__.py
pure_mcp/types/exceptions.py
pure_mcp/types/protocol.py
pure_mcp/types/version.py
pure_mcp-0.1.5.dist-info/licenses/LICENSE
pure_mcp-0.1.5.dist-info/METADATA
pure_mcp-0.1.5.dist-info/WHEEL
pure_mcp-0.1.5.dist-info/top_level.txt
pure_mcp-0.1.5.dist-info/RECORD
