Metadata-Version: 2.4
Name: pure-mcp
Version: 0.1.5
Summary: A lightweight, pure Python implementation of the Model Context Protocol client
Author: John Rood, Osaro Igbinovia
Maintainer: John Rood
License: MIT
Project-URL: Homepage, https://github.com/John-Rood/pure-mcp
Project-URL: Repository, https://github.com/John-Rood/pure-mcp
Project-URL: Issues, https://github.com/John-Rood/pure-mcp/issues
Classifier: Development Status :: 3 - Alpha
Classifier: Intended Audience :: Developers
Classifier: Topic :: Software Development :: Libraries :: Python Modules
Classifier: License :: OSI Approved :: MIT License
Classifier: Programming Language :: Python :: 3
Classifier: Programming Language :: Python :: 3.8
Classifier: Programming Language :: Python :: 3.9
Classifier: Programming Language :: Python :: 3.10
Classifier: Programming Language :: Python :: 3.11
Classifier: Programming Language :: Python :: 3.12
Classifier: Operating System :: OS Independent
Requires-Python: >=3.8
License-File: LICENSE
Requires-Dist: anyio>=3.0.0
Requires-Dist: httpx>=0.25.0
Requires-Dist: httpx-sse>=0.3.0
Requires-Dist: pydantic>=2.0.0
Requires-Dist: jsonschema>=4.0.0
Requires-Dist: typing-extensions>=4.0.0
Provides-Extra: dev
Requires-Dist: pytest>=7.0.0; extra == "dev"
Requires-Dist: pytest-asyncio>=0.21.0; extra == "dev"
Requires-Dist: pytest-cov>=4.0.0; extra == "dev"
Requires-Dist: mypy>=1.0.0; extra == "dev"
Requires-Dist: ruff>=0.1.0; extra == "dev"
Dynamic: license-file
